{
  "version": 1,
  "exercises": [
    {
      "id": "ex0",
      "name": "Squat",
      "group": "Jambes",
      "type": "charge"
    },
    {
      "id": "ex1",
      "name": "Presse à cuisses",
      "group": "Jambes",
      "type": "charge"
    },
    {
      "id": "ex2",
      "name": "Fentes bulgares",
      "group": "Jambes",
      "type": "charge"
    },
    {
      "id": "ex3",
      "name": "Split squat",
      "group": "Jambes",
      "type": "charge"
    },
    {
      "id": "ex4",
      "name": "Fentes marchées (20m)",
      "group": "Jambes",
      "type": "charge"
    },
    {
      "id": "ex5",
      "name": "Leg curl",
      "group": "Jambes",
      "type": "charge"
    },
    {
      "id": "ex6",
      "name": "Leg extension",
      "group": "Jambes",
      "type": "charge"
    },
    {
      "id": "ex7",
      "name": "Tractions",
      "group": "Dos",
      "type": "pdc"
    },
    {
      "id": "ex8",
      "name": "Tractions lestées",
      "group": "Dos",
      "type": "charge"
    },
    {
      "id": "ex9",
      "name": "Tractions négatives lestées",
      "group": "Dos",
      "type": "charge"
    },
    {
      "id": "ex10",
      "name": "Tractions assistées",
      "group": "Dos",
      "type": "charge"
    },
    {
      "id": "ex11",
      "name": "Tirage vertical",
      "group": "Dos",
      "type": "charge"
    },
    {
      "id": "ex12",
      "name": "Tirage horizontal",
      "group": "Dos",
      "type": "charge"
    }
  ],
  "sessions": [
    {
      "id": "seed1",
      "date": "2026-06-01",
      "exos": [
        {
          "exoId": "ex1",
          "sets": [
            {
              "reps": 8,
              "weight": 80
            },
            {
              "reps": 8,
              "weight": 140
            },
            {
              "reps": 8,
              "weight": 140
            },
            {
              "reps": 8,
              "weight": 140
            }
          ]
        },
        {
          "exoId": "ex3",
          "sets": [
            {
              "reps": 8,
              "weight": 24
            },
            {
              "reps": 8,
              "weight": 24
            }
          ]
        },
        {
          "exoId": "ex6",
          "sets": [
            {
              "reps": 8,
              "weight": 55
            },
            {
              "reps": 9,
              "weight": 60
            },
            {
              "reps": 6,
              "weight": 65
            }
          ]
        }
      ]
    },
    {
      "id": "seed2",
      "date": "2026-06-03",
      "exos": [
        {
          "exoId": "ex8",
          "sets": [
            {
              "reps": 4,
              "weight": 5
            },
            {
              "reps": 4,
              "weight": 5
            }
          ]
        },
        {
          "exoId": "ex10",
          "sets": [
            {
              "reps": 8,
              "weight": 21
            },
            {
              "reps": 8,
              "weight": 21
            },
            {
              "reps": 8,
              "weight": 21
            }
          ]
        },
        {
          "exoId": "ex11",
          "sets": [
            {
              "reps": 10,
              "weight": 40
            },
            {
              "reps": 10,
              "weight": 40
            },
            {
              "reps": 10,
              "weight": 40
            }
          ]
        },
        {
          "exoId": "ex12",
          "sets": [
            {
              "reps": 10,
              "weight": 35
            },
            {
              "reps": 10,
              "weight": 35
            },
            {
              "reps": 10,
              "weight": 35
            },
            {
              "reps": 6,
              "weight": 40
            },
            {
              "reps": 4,
              "weight": 30
            }
          ]
        }
      ]
    },
    {
      "id": "seed3",
      "date": "2026-06-08",
      "exos": [
        {
          "exoId": "ex3",
          "sets": [
            {
              "reps": 8,
              "weight": 24
            },
            {
              "reps": 8,
              "weight": 24
            }
          ]
        },
        {
          "exoId": "ex5",
          "sets": [
            {
              "reps": 10,
              "weight": 35
            },
            {
              "reps": 10,
              "weight": 35
            },
            {
              "reps": 10,
              "weight": 35
            }
          ]
        },
        {
          "exoId": "ex6",
          "sets": [
            {
              "reps": 8,
              "weight": 55
            },
            {
              "reps": 9,
              "weight": 60
            },
            {
              "reps": 6,
              "weight": 65
            }
          ]
        }
      ]
    },
    {
      "id": "seed4",
      "date": "2026-06-10",
      "exos": [
        {
          "exoId": "ex8",
          "sets": [
            {
              "reps": 4,
              "weight": 5
            },
            {
              "reps": 4,
              "weight": 5
            }
          ]
        },
        {
          "exoId": "ex10",
          "sets": [
            {
              "reps": 8,
              "weight": 21
            },
            {
              "reps": 8,
              "weight": 21
            },
            {
              "reps": 8,
              "weight": 21
            }
          ]
        },
        {
          "exoId": "ex11",
          "sets": [
            {
              "reps": 10,
              "weight": 40
            },
            {
              "reps": 10,
              "weight": 40
            },
            {
              "reps": 10,
              "weight": 40
            }
          ]
        },
        {
          "exoId": "ex12",
          "sets": [
            {
              "reps": 10,
              "weight": 35
            },
            {
              "reps": 10,
              "weight": 35
            },
            {
              "reps": 10,
              "weight": 35
            },
            {
              "reps": 6,
              "weight": 40
            },
            {
              "reps": 4,
              "weight": 30
            }
          ]
        }
      ]
    },
    {
      "id": "seed5",
      "date": "2026-06-12",
      "exos": [
        {
          "exoId": "ex4",
          "sets": [
            {
              "reps": 1,
              "weight": 24
            },
            {
              "reps": 1,
              "weight": 32
            },
            {
              "reps": 1,
              "weight": 32
            },
            {
              "reps": 1,
              "weight": 40
            }
          ]
        },
        {
          "exoId": "ex6",
          "sets": [
            {
              "reps": 10,
              "weight": 55
            },
            {
              "reps": 8,
              "weight": 65
            },
            {
              "reps": 8,
              "weight": 65
            }
          ]
        }
      ]
    },
    {
      "id": "seed6",
      "date": "2026-06-15",
      "exos": [
        {
          "exoId": "ex1",
          "sets": [
            {
              "reps": 10,
              "weight": 90
            },
            {
              "reps": 10,
              "weight": 130
            },
            {
              "reps": 8,
              "weight": 160
            },
            {
              "reps": 8,
              "weight": 160
            }
          ]
        },
        {
          "exoId": "ex5",
          "sets": [
            {
              "reps": 8,
              "weight": 30
            },
            {
              "reps": 8,
              "weight": 30
            },
            {
              "reps": 8,
              "weight": 30
            }
          ]
        },
        {
          "exoId": "ex6",
          "sets": [
            {
              "reps": 8,
              "weight": 55
            },
            {
              "reps": 8,
              "weight": 60
            },
            {
              "reps": 8,
              "weight": 60
            },
            {
              "reps": 8,
              "weight": 65
            }
          ]
        }
      ]
    },
    {
      "id": "xb0hxkhh",
      "date": "2026-07-01",
      "exos": [
        {
          "exoId": "ex1",
          "sets": [
            {
              "reps": 10,
              "weight": 160
            },
            {
              "reps": 10,
              "weight": 160
            },
            {
              "reps": 8,
              "weight": 180
            }
          ]
        },
        {
          "exoId": "ex3",
          "sets": [
            {
              "reps": 10,
              "weight": 16
            },
            {
              "reps": 8,
              "weight": 28
            },
            {
              "reps": 8,
              "weight": 28
            }
          ]
        }
      ]
    },
    {
      "id": "xznwlq5f",
      "date": "2026-07-02",
      "exos": [
        {
          "exoId": "ex5",
          "sets": [
            {
              "reps": 8,
              "weight": 42.5
            },
            {
              "reps": 8,
              "weight": 42.5
            },
            {
              "reps": 8,
              "weight": 42.5
            }
          ]
        },
        {
          "exoId": "ex6",
          "sets": [
            {
              "reps": 8,
              "weight": 55
            },
            {
              "reps": 10,
              "weight": 65
            },
            {
              "reps": 10,
              "weight": 65
            },
            {
              "reps": 7,
              "weight": 65
            },
            {
              "reps": 4,
              "weight": 55
            }
          ]
        }
      ]
    }
  ]
}